gbfr_auto_restart-0.3.0.dist-info/METADATA
gbfr_auto_restart-0.3.0.dist-info/WHEEL
gbfr_auto_restart-0.3.0.dist-info/entry_points.txt
gbfr_auto_restart-0.3.0.dist-info/licenses/LICENSE
gbfr_auto_restart.py
gbfr_auto_restart-0.3.0.dist-info/RECORD
