Metadata-Version: 2.1
Name: gbfr-auto-restart
Version: 0.3.0
Summary: Granblue Fantasy Relink Auto Restart
Keywords: gbfr
Author-Email: Dowon <ks2515@naver.com>
License: MIT
Classifier: Topic :: Games/Entertainment
Classifier: Topic :: Games/Entertainment :: Role-Playing
Classifier: Operating System :: Microsoft :: Windows
Classifier: License :: OSI Approved :: MIT License
Project-URL: Repository, https://github.com/Bing-su/gbfr_auto_restart
Requires-Python: >=3.9
Requires-Dist: pyscreeze
Requires-Dist: pillow
Requires-Dist: rich
Requires-Dist: opencv-python
Requires-Dist: pydirectinput-rgx
Requires-Dist: black; extra == "dev"
Requires-Dist: ruff; extra == "dev"
Requires-Dist: pre-commit; extra == "dev"
Requires-Dist: nuitka>=2; extra == "build"
Provides-Extra: dev
Provides-Extra: build
